vigilante/__init__.py
vigilante/config.py
vigilante/core.py
vigilante/nightcrawler.py
vigilante/scraptor.py
vigilante/session.py
vigilante/utils.py
vigilante/version.py
vigilante-0.2.3.dist-info/licenses/LICENSE
vigilante-0.2.3.dist-info/METADATA
vigilante-0.2.3.dist-info/WHEEL
vigilante-0.2.3.dist-info/top_level.txt
vigilante-0.2.3.dist-info/RECORD
