Metadata-Version: 2.4
Name: vigilante
Version: 0.2.3
Summary: Dark Web Killer
Home-page: https://github.com/realyavuzbey/vigilante
Author: Yavuz Bey
Requires-Python: >=3.8
License-File: LICENSE
Requires-Dist: requests[socks]
Requires-Dist: beautifulsoup4
Requires-Dist: stem
Requires-Dist: lxml
Requires-Dist: opencv-python
Requires-Dist: numpy
Requires-Dist: plyer
Requires-Dist: rstr
Requires-Dist: torpy
Requires-Dist: faker
Requires-Dist: click
Requires-Dist: pymediainfo
Requires-Dist: exifread
Requires-Dist: pillow
Requires-Dist: python-docx
Requires-Dist: yt-dlp
Requires-Dist: colorama
Requires-Dist: aiohttp
Requires-Dist: aiofiles
Requires-Dist: python-dotenv
Requires-Dist: pycountry
Requires-Dist: dnspython
Requires-Dist: tldextract
Requires-Dist: python-whois
Requires-Dist: fake-useragent
Requires-Dist: tqdm
Requires-Dist: python-dateutil
Requires-Dist: urllib3
Requires-Dist: 2captcha-python
Dynamic: author
Dynamic: home-page
Dynamic: license-file
Dynamic: requires-dist
Dynamic: requires-python
Dynamic: summary
